ongtrum/__init__.py
ongtrum/annotation.py
ongtrum/benchmark.py
ongtrum/ongtrum.py
ongtrum/session.py
ongtrum/core/__init__.py
ongtrum/core/ast_parser.c
ongtrum/core/ast_parser.cp312-win_amd64.pyd
ongtrum/core/ast_parser.pyx
ongtrum/core/fs_scanner.c
ongtrum/core/fs_scanner.cp312-win_amd64.pyd
ongtrum/core/fs_scanner.pyx
python_ongtrum-0.1.4.dist-info/licenses/LICENSE
python_ongtrum-0.1.4.dist-info/METADATA
python_ongtrum-0.1.4.dist-info/WHEEL
python_ongtrum-0.1.4.dist-info/entry_points.txt
python_ongtrum-0.1.4.dist-info/top_level.txt
python_ongtrum-0.1.4.dist-info/RECORD
