Metadata-Version: 2.4
Name: python-ongtrum
Version: 0.1.4
Summary: Ongtrum is a Python test runner designed for speed.
Author-email: Omer Menashe <unspecified@mail.com>
License: MIT
Project-URL: Source, https://github.com/iamomerm/python-ongtrum
Keywords: python-ongtrum,test
Classifier: Programming Language :: Python :: 3
Classifier: License :: OSI Approved :: MIT License
Classifier: Operating System :: OS Independent
Requires-Python: >=3.7
License-File: LICENSE
Requires-Dist: PyYAML>=6.0.3
Requires-Dist: Cython>=3.2.2
Provides-Extra: dev
Requires-Dist: pytest>=7.0; extra == "dev"
Dynamic: license-file
